odoo/addons/shift_portal/README.rst
odoo/addons/shift_portal/__init__.py
odoo/addons/shift_portal/__manifest__.py
odoo/addons/shift_portal/controllers/__init__.py
odoo/addons/shift_portal/controllers/main.py
odoo/addons/shift_portal/controllers/shift_grid_utils.py
odoo/addons/shift_portal/data/res_config_data.xml
odoo/addons/shift_portal/i18n/fr_BE.po
odoo/addons/shift_portal/i18n/nl_BE.po
odoo/addons/shift_portal/i18n/shift_portal.pot
odoo/addons/shift_portal/models/__init__.py
odoo/addons/shift_portal/models/res_config.py
odoo/addons/shift_portal/models/website.py
odoo/addons/shift_portal/readme/CONTRIBUTORS.rst
odoo/addons/shift_portal/readme/DESCRIPTION.rst
odoo/addons/shift_portal/static/description/index.html
odoo/addons/shift_portal/static/src/js/script.js
odoo/addons/shift_portal/views/my_shift_website_templates.xml
odoo/addons/shift_portal/views/res_config_views.xml
odoo/addons/shift_portal/views/shift_website_templates.xml
odoo_addon_shift_portal-16.0.1.1.0.2.dist-info/METADATA
odoo_addon_shift_portal-16.0.1.1.0.2.dist-info/WHEEL
odoo_addon_shift_portal-16.0.1.1.0.2.dist-info/top_level.txt
odoo_addon_shift_portal-16.0.1.1.0.2.dist-info/RECORD
