Metadata-Version: 2.1
Name: odoo-addon-shift_portal
Version: 16.0.1.1.0.2
Requires-Python: >=3.10
Requires-Dist: odoo-addon-shift>=16.0dev,<16.1dev
Requires-Dist: odoo>=16.0a,<16.1dev
Summary: Show available shifts for regular and irregular workers on the website and let workers manage their shifts with an easy web interface.
Home-page: https://github.com/beescoop/Obeesdoo
License: AGPL-3
Author: Coop IT Easy SC
Classifier: Programming Language :: Python
Classifier: Framework :: Odoo
Classifier: Framework :: Odoo :: 16.0
Classifier: License :: OSI Approved :: GNU Affero General Public License v3
